pyttanko.py
pyttanko-2.1.0.dist-info/METADATA
pyttanko-2.1.0.dist-info/WHEEL
pyttanko-2.1.0.dist-info/top_level.txt
pyttanko-2.1.0.dist-info/RECORD
