Metadata-Version: 2.1
Name: pyttanko
Version: 2.1.0
Summary: osu! pp and difficulty calculator
Home-page: https://github.com/Francesco149/pyttanko
Author: Franc[e]sco
Author-email: lolisamurai@tfwno.gf
License: Unlicense
Keywords: osu! osu
Platform: UNKNOWN
Classifier: Programming Language :: Python :: 2
Classifier: Programming Language :: Python :: 3
Classifier: Intended Audience :: Developers
Classifier: License :: Public Domain
Classifier: Topic :: Software Development :: Libraries
Classifier: Topic :: Utilities
